{"id": "2BYody7JX_w", "title": "LOS PANCHOS - RAYITO DE LUNA", "formats": [{"asr": 48000, "filesize": 1155808, "format_id": "249", "format_note": "tiny", "fps": null, "height": null, "quality": 0, "tbr": 54.142, "url": "https://rr1---sn-0opoxu-ihvr.googlevideo.com/videoplayback?expire=1670725990&ei=Bu2UY4ulJaGGsfIP_eCiwA8&ip=189.173.225.87&id=o-AJhjlY7ieJeErMP7IEitRxUs_0Mc_KsiFca3XXNVk-7S&itag=249&source=youtube&requiressl=yes&mh=v5&mm=31%2C29&mn=sn-0opoxu-ihvr%2Csn-q4flrnee&ms=au%2Crdu&mv=m&mvi=1&pl=24&initcwndbps=777500&vprv=1&mime=audio%2Fwebm&ns=j0qqX3Nl6gnr2IecQoL3Z4wJ&gir=yes&clen=1155808&dur=170.781&lmt=1541180307371711&mt=1670704150&fvip=5&keepalive=yes&fexp=24001373%2C24007246&c=WEB&txp=5511222&n=ICqElugTWcTVpO_2n&sparams=expire%2Cei%2Cip%2Cid%2Citag%2Csource%2Crequiressl%2Cvprv%2Cmime%2Cns%2Cgir%2Cclen%2Cdur%2Clmt&lsparams=mh%2Cmm%2Cmn%2Cms%2Cmv%2Cmvi%2Cpl%2Cinitcwndbps&lsig=AG3C_xAwRQIgF89_frOUz4Go696izJyjH54d1-d7XZ-bFxVzs-fHiTECIQDKxLxfrmbAlqGN4ZFWpkZk6Gw6BKa8MB0_im602Hd8ew%3D%3D&sig=AOq0QJ8wRQIgEIwT2CPy0NqAqHjHzmso115j1KK03bvmefN_Q6Jiw7UCIQDxnPGTW4S9peUzVI225mP4Oh_vcj1KtgxZ6_bo50YPzQ==", "width": null, "ext": "webm", "vcodec": "none", "acodec": "opus", "abr": 54.142, "downloader_options": {"http_chunk_size": 10485760}, "container": "webm_dash", "format": "249 - audio only (tiny)", "protocol": "https", "http_headers": {"User-Agent": "Mozilla/5.0 (Windows NT 10.0; Win64; x64) AppleWebKit/537.36 (KHTML, like Gecko) Chrome/73.0.3653.0 Safari/537.36", "Accept-Charset": "ISO-8859-1,utf-8;q=0.7,*;q=0.7", "Accept": "text/html,application/xhtml+xml,application/xml;q=0.9,*/*;q=0.8", "Accept-Encoding": "gzip, deflate", "Accept-Language": "en-us,en;q=0.5"}}, {"asr": 48000, "filesize": 1520167, "format_id": "250", "format_note": "tiny", "fps": null, "height": null, "quality": 0, "tbr": 71.21, "url": "https://rr1---sn-0opoxu-ihvr.googlevideo.com/videoplayback?expire=1670725990&ei=Bu2UY4ulJaGGsfIP_eCiwA8&ip=189.173.225.87&id=o-AJhjlY7ieJeErMP7IEitRxUs_0Mc_KsiFca3XXNVk-7S&itag=250&source=youtube&requiressl=yes&mh=v5&mm=31%2C29&mn=sn-0opoxu-ihvr%2Csn-q4flrnee&ms=au%2Crdu&mv=m&mvi=1&pl=24&initcwndbps=777500&vprv=1&mime=audio%2Fwebm&ns=j0qqX3Nl6gnr2IecQoL3Z4wJ&gir=yes&clen=1520167&dur=170.781&lmt=1541180271973245&mt=1670704150&fvip=5&keepalive=yes&fexp=24001373%2C24007246&c=WEB&txp=5511222&n=ICqElugTWcTVpO_2n&sparams=expire%2Cei%2Cip%2Cid%2Citag%2Csource%2Crequiressl%2Cvprv%2Cmime%2Cns%2Cgir%2Cclen%2Cdur%2Clmt&lsparams=mh%2Cmm%2Cmn%2Cms%2Cmv%2Cmvi%2Cpl%2Cinitcwndbps&lsig=AG3C_xAwRAIgKn31Z1H74fJSKQtx2VnGEmz3Kdq9R02nMqQVbJ4DukwCIBq5NcLpPJCEWvN-TE76HWwLn6L1LcGyBOaUPrcfwmg3&sig=AOq0QJ8wRgIhAP1KljyRkAzEqvF-Ien6ItGTCdqRFdpqJYs-hDynLCKGAiEAsKxxZMZpxMJgJBOtCEImjSHrtSw49OlLTSXJaOL7rfA=", "width": null, "ext": "webm", "vcodec": "none", "acodec": "opus", "abr": 71.21, "downloader_options": {"http_chunk_size": 10485760}, "container": "webm_dash", "format": "250 - audio only (tiny)", "protocol": "https", "http_headers": {"User-Agent": "Mozilla/5.0 (Windows NT 10.0; Win64; x64) AppleWebKit/537.36 (KHTML, like Gecko) Chrome/73.0.3653.0 Safari/537.36", "Accept-Charset": "ISO-8859-1,utf-8;q=0.7,*;q=0.7", "Accept": "text/html,application/xhtml+xml,application/xml;q=0.9,*/*;q=0.8", "Accept-Encoding": "gzip, deflate", "Accept-Language": "en-us,en;q=0.5"}}, {"asr": 44100, "filesize": 2765447, "format_id": "140", "format_note": "tiny", "fps": null, "height": null, "quality": 0, "tbr": 129.507, "url": "https://rr1---sn-0opoxu-ihvr.googlevideo.com/videoplayback?expire=1670725990&ei=Bu2UY4ulJaGGsfIP_eCiwA8&ip=189.173.225.87&id=o-AJhjlY7ieJeErMP7IEitRxUs_0Mc_KsiFca3XXNVk-7S&itag=140&source=youtube&requiressl=yes&mh=v5&mm=31%2C29&mn=sn-0opoxu-ihvr%2Csn-q4flrnee&ms=au%2Crdu&mv=m&mvi=1&pl=24&initcwndbps=777500&vprv=1&mime=audio%2Fmp4&ns=j0qqX3Nl6gnr2IecQoL3Z4wJ&gir=yes&clen=2765447&dur=170.829&lmt=1580146648373644&mt=1670704150&fvip=5&keepalive=yes&fexp=24001373%2C24007246&c=WEB&txp=5531432&n=ICqElugTWcTVpO_2n&sparams=expire%2Cei%2Cip%2Cid%2Citag%2Csource%2Crequiressl%2Cvprv%2Cmime%2Cns%2Cgir%2Cclen%2Cdur%2Clmt&lsparams=mh%2Cmm%2Cmn%2Cms%2Cmv%2Cmvi%2Cpl%2Cinitcwndbps&lsig=AG3C_xAwRQIhAKBkp4WX5h6iGDbYTXX4VK5fVvXZ0JvGl0QIGzk8RkH5AiBU8YiXdzdCIIihIZsLtx0IbA-YAAyxLH5vIY-qemxa_g%3D%3D&sig=AOq0QJ8wRQIgLAaxcGBdI0yJ1hnoQQrgb6gnJ7Jff0t6s2L-2qk4204CIQDJz5TXjenThC7k7Bgdppz9TM7R-fS8UTxl5rq93rsv4A==", "width": null, "ext": "m4a", "vcodec": "none", "acodec": "mp4a.40.2", "abr": 129.507, "downloader_options": {"http_chunk_size": 10485760}, "container": "m4a_dash", "format": "140 - audio only (tiny)", "protocol": "https", "http_headers": {"User-Agent": "Mozilla/5.0 (Windows NT 10.0; Win64; x64) AppleWebKit/537.36 (KHTML, like Gecko) Chrome/73.0.3653.0 Safari/537.36", "Accept-Charset": "ISO-8859-1,utf-8;q=0.7,*;q=0.7", "Accept": "text/html,application/xhtml+xml,application/xml;q=0.9,*/*;q=0.8", "Accept-Encoding": "gzip, deflate", "Accept-Language": "en-us,en;q=0.5"}}, {"asr": 48000, "filesize": 2991693, "format_id": "251", "format_note": "tiny", "fps": null, "height": null, "quality": 0, "tbr": 140.141, "url": "https://rr1---sn-0opoxu-ihvr.googlevideo.com/videoplayback?expire=1670725990&ei=Bu2UY4ulJaGGsfIP_eCiwA8&ip=189.173.225.87&id=o-AJhjlY7ieJeErMP7IEitRxUs_0Mc_KsiFca3XXNVk-7S&itag=251&source=youtube&requiressl=yes&mh=v5&mm=31%2C29&mn=sn-0opoxu-ihvr%2Csn-q4flrnee&ms=au%2Crdu&mv=m&mvi=1&pl=24&initcwndbps=777500&vprv=1&mime=audio%2Fwebm&ns=j0qqX3Nl6gnr2IecQoL3Z4wJ&gir=yes&clen=2991693&dur=170.781&lmt=1541180401855497&mt=1670704150&fvip=5&keepalive=yes&fexp=24001373%2C24007246&c=WEB&txp=5511222&n=ICqElugTWcTVpO_2n&sparams=expire%2Cei%2Cip%2Cid%2Citag%2Csource%2Crequiressl%2Cvprv%2Cmime%2Cns%2Cgir%2Cclen%2Cdur%2Clmt&lsparams=mh%2Cmm%2Cmn%2Cms%2Cmv%2Cmvi%2Cpl%2Cinitcwndbps&lsig=AG3C_xAwRgIhALJNfVQklFPaM2lpk08i2oeAckXhDt2LAU0iSUPjBRDmAiEAhK1IJwSIIWj2YeFDG8QDkBp7Nn2ISfmk31cbijER_S4%3D&sig=AOq0QJ8wRAIgXODI5E_2yY-Dup2mH_gBZJemR1I95u1TgubPcAebgHACIGJFuO7JNAH_M7LLG5QbV4cpGcie5Z29BY-NXEYvyNeD", "width": null, "ext": "webm", "vcodec": "none", "acodec": "opus", "abr": 140.141, "downloader_options": {"http_chunk_size": 10485760}, "container": "webm_dash", "format": "251 - audio only (tiny)", "protocol": "https", "http_headers": {"User-Agent": "Mozilla/5.0 (Windows NT 10.0; Win64; x64) AppleWebKit/537.36 (KHTML, like Gecko) Chrome/73.0.3653.0 Safari/537.36", "Accept-Charset": "ISO-8859-1,utf-8;q=0.7,*;q=0.7", "Accept": "text/html,application/xhtml+xml,application/xml;q=0.9,*/*;q=0.8", "Accept-Encoding": "gzip, deflate", "Accept-Language": "en-us,en;q=0.5"}}, {"asr": null, "filesize": 348503, "format_id": "160", "format_note": "144p", "fps": 30, "height": 144, "quality": 0, "tbr": 16.332, "url": "https://rr1---sn-0opoxu-ihvr.googlevideo.com/videoplayback?expire=1670725990&ei=Bu2UY4ulJaGGsfIP_eCiwA8&ip=189.173.225.87&id=o-AJhjlY7ieJeErMP7IEitRxUs_0Mc_KsiFca3XXNVk-7S&itag=160&aitags=133%2C134%2C135%2C160%2C242%2C243%2C244%2C278%2C394%2C395%2C396%2C397&source=youtube&requiressl=yes&mh=v5&mm=31%2C29&mn=sn-0opoxu-ihvr%2Csn-q4flrnee&ms=au%2Crdu&mv=m&mvi=1&pl=24&initcwndbps=777500&vprv=1&mime=video%2Fmp4&ns=j0qqX3Nl6gnr2IecQoL3Z4wJ&gir=yes&clen=348503&dur=170.699&lmt=1580146880501708&mt=1670704150&fvip=5&keepalive=yes&fexp=24001373%2C24007246&c=WEB&txp=5532432&n=ICqElugTWcTVpO_2n&sparams=expire%2Cei%2Cip%2Cid%2Caitags%2Csource%2Crequiressl%2Cvprv%2Cmime%2Cns%2Cgir%2Cclen%2Cdur%2Clmt&lsparams=mh%2Cmm%2Cmn%2Cms%2Cmv%2Cmvi%2Cpl%2Cinitcwndbps&lsig=AG3C_xAwRQIhAOKRJ0zCap_L0M0oTUGalBqcfPM7LS28jQDIJu6TKfMBAiA2OyVbXxe8NF4-9HZ0igdJuVKaDEFY2Z9TXTxRvKscKw%3D%3D&sig=AOq0QJ8wRgIhANKS0bKNZnv1Xzd8lhjCDhRPYdFQXN_XU8eAJwzNJw2oAiEAs9NYbJSVfr-p61z5I8xxxQui4vyVkSNcEg1zgIY3eJM=", "width": 192, "ext": "mp4", "vcodec": "avc1.4d400c", "acodec": "none", "vbr": 16.332, "downloader_options": {"http_chunk_size": 10485760}, "container": "mp4_dash", "format": "160 - 192x144 (144p)", "protocol": "https", "http_headers": {"User-Agent": "Mozilla/5.0 (Windows NT 10.0; Win64; x64) AppleWebKit/537.36 (KHTML, like Gecko) Chrome/73.0.3653.0 Safari/537.36", "Accept-Charset": "ISO-8859-1,utf-8;q=0.7,*;q=0.7", "Accept": "text/html,application/xhtml+xml,application/xml;q=0.9,*/*;q=0.8", "Accept-Encoding": "gzip, deflate", "Accept-Language": "en-us,en;q=0.5"}}, {"asr": null, "filesize": 548863, "format_id": "278", "format_note": "144p", "fps": 30, "height": 144, "quality": 0, "tbr": 25.722, "url": "https://rr1---sn-0opoxu-ihvr.googlevideo.com/videoplayback?expire=1670725990&ei=Bu2UY4ulJaGGsfIP_eCiwA8&ip=189.173.225.87&id=o-AJhjlY7ieJeErMP7IEitRxUs_0Mc_KsiFca3XXNVk-7S&itag=278&aitags=133%2C134%2C135%2C160%2C242%2C243%2C244%2C278%2C394%2C395%2C396%2C397&source=youtube&requiressl=yes&mh=v5&mm=31%2C29&mn=sn-0opoxu-ihvr%2Csn-q4flrnee&ms=au%2Crdu&mv=m&mvi=1&pl=24&initcwndbps=777500&vprv=1&mime=video%2Fwebm&ns=j0qqX3Nl6gnr2IecQoL3Z4wJ&gir=yes&clen=548863&dur=170.700&lmt=1541180021987611&mt=1670704150&fvip=5&keepalive=yes&fexp=24001373%2C24007246&c=WEB&txp=5532432&n=ICqElugTWcTVpO_2n&sparams=expire%2Cei%2Cip%2Cid%2Caitags%2Csource%2Crequiressl%2Cvprv%2Cmime%2Cns%2Cgir%2Cclen%2Cdur%2Clmt&lsparams=mh%2Cmm%2Cmn%2Cms%2Cmv%2Cmvi%2Cpl%2Cinitcwndbps&lsig=AG3C_xAwRQIgBnxHzTt6cFO8gDSWN-IlpJWZtK26VeumSXxx3vocPOACIQDhjqXAaeULqEkc-cx0FLHwatGKrYsByf0VO6th76Z7Ww%3D%3D&sig=AOq0QJ8wRQIgXY0C9JVBZGzhH5h9EHHVS5jn1estaBmpHPiR3oW_Nd8CIQDjb4YDING1Qgs53Z2_NXlSfr70KxepxvThXc8-g0TTaQ==", "width": 192, "ext": "webm", "vcodec": "vp9", "acodec": "none", "vbr": 25.722, "downloader_options": {"http_chunk_size": 10485760}, "container": "webm_dash", "format": "278 - 192x144 (144p)", "protocol": "https", "http_headers": {"User-Agent": "Mozilla/5.0 (Windows NT 10.0; Win64; x64) AppleWebKit/537.36 (KHTML, like Gecko) Chrome/73.0.3653.0 Safari/537.36", "Accept-Charset": "ISO-8859-1,utf-8;q=0.7,*;q=0.7", "Accept": "text/html,application/xhtml+xml,application/xml;q=0.9,*/*;q=0.8", "Accept-Encoding": "gzip, deflate", "Accept-Language": "en-us,en;q=0.5"}}, {"asr": null, "filesize": 663017, "format_id": "394", "format_note": "144p", "fps": 30, "height": 144, "quality": 0, "tbr": 31.073, "url": "https://rr1---sn-0opoxu-ihvr.googlevideo.com/videoplayback?expire=1670725990&ei=Bu2UY4ulJaGGsfIP_eCiwA8&ip=189.173.225.87&id=o-AJhjlY7ieJeErMP7IEitRxUs_0Mc_KsiFca3XXNVk-7S&itag=394&aitags=133%2C134%2C135%2C160%2C242%2C243%2C244%2C278%2C394%2C395%2C396%2C397&source=youtube&requiressl=yes&mh=v5&mm=31%2C29&mn=sn-0opoxu-ihvr%2Csn-q4flrnee&ms=au%2Crdu&mv=m&mvi=1&pl=24&initcwndbps=777500&vprv=1&mime=video%2Fmp4&ns=j0qqX3Nl6gnr2IecQoL3Z4wJ&gir=yes&clen=663017&dur=170.699&lmt=1633393608092538&mt=1670704150&fvip=5&keepalive=yes&fexp=24001373%2C24007246&c=WEB&txp=5532434&n=ICqElugTWcTVpO_2n&sparams=expire%2Cei%2Cip%2Cid%2Caitags%2Csource%2Crequiressl%2Cvprv%2Cmime%2Cns%2Cgir%2Cclen%2Cdur%2Clmt&lsparams=mh%2Cmm%2Cmn%2Cms%2Cmv%2Cmvi%2Cpl%2Cinitcwndbps&lsig=AG3C_xAwRAIgZA4kpzjiUUQfIy8eYfZdnC3moKFGMZmGjK_LSFLQkAwCIAcsWUYJBxa4QAuwpxnwdyFu3KXnSDeWplqGLQgUHteW&sig=AOq0QJ8wRQIgO7HZE3CSJrBWy6BmLhMUZVvgbbCLt1AWFBNIofjGYqECIQCzT-zQvrpUIXJeHdhgmBflprEr2eC3thXC27ovBgv_-g==", "width": 192, "ext": "mp4", "vcodec": "av01.0.00M.08", "acodec": "none", "vbr": 31.073, "downloader_options": {"http_chunk_size": 10485760}, "container": "mp4_dash", "format": "394 - 192x144 (144p)", "protocol": "https", "http_headers": {"User-Agent": "Mozilla/5.0 (Windows NT 10.0; Win64; x64) AppleWebKit/537.36 (KHTML, like Gecko) Chrome/73.0.3653.0 Safari/537.36", "Accept-Charset": "ISO-8859-1,utf-8;q=0.7,*;q=0.7", "Accept": "text/html,application/xhtml+xml,application/xml;q=0.9,*/*;q=0.8", "Accept-Encoding": "gzip, deflate", "Accept-Language": "en-us,en;q=0.5"}}, {"asr": null, "filesize": 563185, "format_id": "133", "format_note": "240p", "fps": 30, "height": 240, "quality": 1, "tbr": 26.394, "url": "https://rr1---sn-0opoxu-ihvr.googlevideo.com/videoplayback?expire=1670725990&ei=Bu2UY4ulJaGGsfIP_eCiwA8&ip=189.173.225.87&id=o-AJhjlY7ieJeErMP7IEitRxUs_0Mc_KsiFca3XXNVk-7S&itag=133&aitags=133%2C134%2C135%2C160%2C242%2C243%2C244%2C278%2C394%2C395%2C396%2C397&source=youtube&requiressl=yes&mh=v5&mm=31%2C29&mn=sn-0opoxu-ihvr%2Csn-q4flrnee&ms=au%2Crdu&mv=m&mvi=1&pl=24&initcwndbps=777500&vprv=1&mime=video%2Fmp4&ns=j0qqX3Nl6gnr2IecQoL3Z4wJ&gir=yes&clen=563185&dur=170.699&lmt=1580146880502093&mt=1670704150&fvip=5&keepalive=yes&fexp=24001373%2C24007246&c=WEB&txp=5532432&n=ICqElugTWcTVpO_2n&sparams=expire%2Cei%2Cip%2Cid%2Caitags%2Csource%2Crequiressl%2Cvprv%2Cmime%2Cns%2Cgir%2Cclen%2Cdur%2Clmt&lsparams=mh%2Cmm%2Cmn%2Cms%2Cmv%2Cmvi%2Cpl%2Cinitcwndbps&lsig=AG3C_xAwRgIhAJ0WeJl-IQtXDU7EVjZ-D_OYQjGrJooWNTDa0-1JNVhLAiEAnODp07hdUJgDNer4gNHjROOcHy-lbr0QGCUW4U3zHqY%3D&sig=AOq0QJ8wRQIgBU04xRB5ZKDEORG7cqhasBi-HpS03ECoSzq2i9c12g0CIQCgfw-I83KaIoDHmXZUVQs_0aeZbdKEJR76zoM1Jr6JCg==", "width": 320, "ext": "mp4", "vcodec": "avc1.4d400d", "acodec": "none", "vbr": 26.394, "downloader_options": {"http_chunk_size": 10485760}, "container": "mp4_dash", "format": "133 - 320x240 (240p)", "protocol": "https", "http_headers": {"User-Agent": "Mozilla/5.0 (Windows NT 10.0; Win64; x64) AppleWebKit/537.36 (KHTML, like Gecko) Chrome/73.0.3653.0 Safari/537.36", "Accept-Charset": "ISO-8859-1,utf-8;q=0.7,*;q=0.7", "Accept": "text/html,application/xhtml+xml,application/xml;q=0.9,*/*;q=0.8", "Accept-Encoding": "gzip, deflate", "Accept-Language": "en-us,en;q=0.5"}}, {"asr": null, "filesize": 1086080, "format_id": "395", "format_note": "240p", "fps": 30, "height": 240, "quality": 1, "tbr": 50.9, "url": "https://rr1---sn-0opoxu-ihvr.googlevideo.com/videoplayback?expire=1670725990&ei=Bu2UY4ulJaGGsfIP_eCiwA8&ip=189.173.225.87&id=o-AJhjlY7ieJeErMP7IEitRxUs_0Mc_KsiFca3XXNVk-7S&itag=395&aitags=133%2C134%2C135%2C160%2C242%2C243%2C244%2C278%2C394%2C395%2C396%2C397&source=youtube&requiressl=yes&mh=v5&mm=31%2C29&mn=sn-0opoxu-ihvr%2Csn-q4flrnee&ms=au%2Crdu&mv=m&mvi=1&pl=24&initcwndbps=777500&vprv=1&mime=video%2Fmp4&ns=j0qqX3Nl6gnr2IecQoL3Z4wJ&gir=yes&clen=1086080&dur=170.699&lmt=1633393773845882&mt=1670704150&fvip=5&keepalive=yes&fexp=24001373%2C24007246&c=WEB&txp=5532434&n=ICqElugTWcTVpO_2n&sparams=expire%2Cei%2Cip%2Cid%2Caitags%2Csource%2Crequiressl%2Cvprv%2Cmime%2Cns%2Cgir%2Cclen%2Cdur%2Clmt&lsparams=mh%2Cmm%2Cmn%2Cms%2Cmv%2Cmvi%2Cpl%2Cinitcwndbps&lsig=AG3C_xAwRAIgcfbRsCFXVYuXvhB_YHlPo9Wc686GSSoGMX5hkp8tkPUCIH_q-H09innpODtdXVPqkZ9ccFGqclBILC_utfzXTbWm&sig=AOq0QJ8wRgIhAJrYSO9gJRwrpCnx5TLQof___W6YYio2e-EB82ITi9ReAiEApQL0prMZLIXgb7ztAo7DMd2V639jpoCgV08Ie3uvT_w=", "width": 320, "ext": "mp4", "vcodec": "av01.0.00M.08", "acodec": "none", "vbr": 50.9, "downloader_options": {"http_chunk_size": 10485760}, "container": "mp4_dash", "format": "395 - 320x240 (240p)", "protocol": "https", "http_headers": {"User-Agent": "Mozilla/5.0 (Windows NT 10.0; Win64; x64) AppleWebKit/537.36 (KHTML, like Gecko) Chrome/73.0.3653.0 Safari/537.36", "Accept-Charset": "ISO-8859-1,utf-8;q=0.7,*;q=0.7", "Accept": "text/html,application/xhtml+xml,application/xml;q=0.9,*/*;q=0.8", "Accept-Encoding": "gzip, deflate", "Accept-Language": "en-us,en;q=0.5"}}, {"asr": null, "filesize": 1155792, "format_id": "242", "format_note": "240p", "fps": 30, "height": 240, "quality": 1, "tbr": 54.167, "url": "https://rr1---sn-0opoxu-ihvr.googlevideo.com/videoplayback?expire=1670725990&ei=Bu2UY4ulJaGGsfIP_eCiwA8&ip=189.173.225.87&id=o-AJhjlY7ieJeErMP7IEitRxUs_0Mc_KsiFca3XXNVk-7S&itag=242&aitags=133%2C134%2C135%2C160%2C242%2C243%2C244%2C278%2C394%2C395%2C396%2C397&source=youtube&requiressl=yes&mh=v5&mm=31%2C29&mn=sn-0opoxu-ihvr%2Csn-q4flrnee&ms=au%2Crdu&mv=m&mvi=1&pl=24&initcwndbps=777500&vprv=1&mime=video%2Fwebm&ns=j0qqX3Nl6gnr2IecQoL3Z4wJ&gir=yes&clen=1155792&dur=170.700&lmt=1541180021965804&mt=1670704150&fvip=5&keepalive=yes&fexp=24001373%2C24007246&c=WEB&txp=5532432&n=ICqElugTWcTVpO_2n&sparams=expire%2Cei%2Cip%2Cid%2Caitags%2Csource%2Crequiressl%2Cvprv%2Cmime%2Cns%2Cgir%2Cclen%2Cdur%2Clmt&lsparams=mh%2Cmm%2Cmn%2Cms%2Cmv%2Cmvi%2Cpl%2Cinitcwndbps&lsig=AG3C_xAwRQIhAK5TyX4gEDg8ZInECKhSYR1MuviElvkkwlcBKTr1U9DPAiBiNf-ztIiP68j6e99xL0-ojt2EEJg0hYKVxD8gdIr3Iw%3D%3D&sig=AOq0QJ8wRAIgKFL3ekamVw42hXncl9WJ0XsqGV9gl5ADf3AVe-T-9cMCID3dgq8DzR9Iu5Z-p8AOWVMkJD9zHS3hZ8Xqi8p9oHih", "width": 320, "ext": "webm", "vcodec": "vp9", "acodec": "none", "vbr": 54.167, "downloader_options": {"http_chunk_size": 10485760}, "container": "webm_dash", "format": "242 - 320x240 (240p)", "protocol": "https", "http_headers": {"User-Agent": "Mozilla/5.0 (Windows NT 10.0; Win64; x64) AppleWebKit/537.36 (KHTML, like Gecko) Chrome/73.0.3653.0 Safari/537.36", "Accept-Charset": "ISO-8859-1,utf-8;q=0.7,*;q=0.7", "Accept": "text/html,application/xhtml+xml,application/xml;q=0.9,*/*;q=0.8", "Accept-Encoding": "gzip, deflate", "Accept-Language": "en-us,en;q=0.5"}}, {"asr": null, "filesize": 1182980, "format_id": "134", "format_note": "360p", "fps": 30, "height": 360, "quality": 2, "tbr": 55.441, "url": "https://rr1---sn-0opoxu-ihvr.googlevideo.com/videoplayback?expire=1670725990&ei=Bu2UY4ulJaGGsfIP_eCiwA8&ip=189.173.225.87&id=o-AJhjlY7ieJeErMP7IEitRxUs_0Mc_KsiFca3XXNVk-7S&itag=134&aitags=133%2C134%2C135%2C160%2C242%2C243%2C244%2C278%2C394%2C395%2C396%2C397&source=youtube&requiressl=yes&mh=v5&mm=31%2C29&mn=sn-0opoxu-ihvr%2Csn-q4flrnee&ms=au%2Crdu&mv=m&mvi=1&pl=24&initcwndbps=777500&vprv=1&mime=video%2Fmp4&ns=j0qqX3Nl6gnr2IecQoL3Z4wJ&gir=yes&clen=1182980&dur=170.699&lmt=1580146880502285&mt=1670704150&fvip=5&keepalive=yes&fexp=24001373%2C24007246&c=WEB&txp=5532432&n=ICqElugTWcTVpO_2n&sparams=expire%2Cei%2Cip%2Cid%2Caitags%2Csource%2Crequiressl%2Cvprv%2Cmime%2Cns%2Cgir%2Cclen%2Cdur%2Clmt&lsparams=mh%2Cmm%2Cmn%2Cms%2Cmv%2Cmvi%2Cpl%2Cinitcwndbps&lsig=AG3C_xAwRgIhAL4pxzDiZDaQ1Op8tts_okoUImeSI1y92e3Ev-W0ztiZAiEA3o3aWvdQQwf5SGknpNKmplRmLzwbOnXeHdzn8UbLMu8%3D&sig=AOq0QJ8wRQIgWZn4hI3MtzUuEBeWB_oKnqg2ucAS_QuztaGejxn3y8QCIQDyBj18fB-hF0NpG3fP2tjtWYXk7wWdRjL3Xhaaer6DkA==", "width": 480, "ext": "mp4", "vcodec": "avc1.4d401e", "acodec": "none", "vbr": 55.441, "downloader_options": {"http_chunk_size": 10485760}, "container": "mp4_dash", "format": "134 - 480x360 (360p)", "protocol": "https", "http_headers": {"User-Agent": "Mozilla/5.0 (Windows NT 10.0; Win64; x64) AppleWebKit/537.36 (KHTML, like Gecko) Chrome/73.0.3653.0 Safari/537.36", "Accept-Charset": "ISO-8859-1,utf-8;q=0.7,*;q=0.7", "Accept": "text/html,application/xhtml+xml,application/xml;q=0.9,*/*;q=0.8", "Accept-Encoding": "gzip, deflate", "Accept-Language": "en-us,en;q=0.5"}}, {"asr": null, "filesize": 1720275, "format_id": "396", "format_note": "360p", "fps": 30, "height": 360, "quality": 2, "tbr": 80.622, "url": "https://rr1---sn-0opoxu-ihvr.googlevideo.com/videoplayback?expire=1670725990&ei=Bu2UY4ulJaGGsfIP_eCiwA8&ip=189.173.225.87&id=o-AJhjlY7ieJeErMP7IEitRxUs_0Mc_KsiFca3XXNVk-7S&itag=396&aitags=133%2C134%2C135%2C160%2C242%2C243%2C244%2C278%2C394%2C395%2C396%2C397&source=youtube&requiressl=yes&mh=v5&mm=31%2C29&mn=sn-0opoxu-ihvr%2Csn-q4flrnee&ms=au%2Crdu&mv=m&mvi=1&pl=24&initcwndbps=777500&vprv=1&mime=video%2Fmp4&ns=j0qqX3Nl6gnr2IecQoL3Z4wJ&gir=yes&clen=1720275&dur=170.699&lmt=1633393764182548&mt=1670704150&fvip=5&keepalive=yes&fexp=24001373%2C24007246&c=WEB&txp=5532434&n=ICqElugTWcTVpO_2n&sparams=expire%2Cei%2Cip%2Cid%2Caitags%2Csource%2Crequiressl%2Cvprv%2Cmime%2Cns%2Cgir%2Cclen%2Cdur%2Clmt&lsparams=mh%2Cmm%2Cmn%2Cms%2Cmv%2Cmvi%2Cpl%2Cinitcwndbps&lsig=AG3C_xAwRgIhAPf3tzEpXp4l-7OE8t7m3KL33NiaX5JXX0cTbEtt_plpAiEAiqB4wHKyAGhzLIxDttS0I0RtwrKYItxtyFgpOKBXAAw%3D&sig=AOq0QJ8wRQIgMOB73fzeom7eyRg6O5SRlFrE1C6AnYuJBT_--LOCYaICIQDLD54c168-0IR76JcjKJDF-s75VPTSWR_0lE9D7gq4nA==", "width": 480, "ext": "mp4", "vcodec": "av01.0.01M.08", "acodec": "none", "vbr": 80.622, "downloader_options": {"http_chunk_size": 10485760}, "container": "mp4_dash", "format": "396 - 480x360 (360p)", "protocol": "https", "http_headers": {"User-Agent": "Mozilla/5.0 (Windows NT 10.0; Win64; x64) AppleWebKit/537.36 (KHTML, like Gecko) Chrome/73.0.3653.0 Safari/537.36", "Accept-Charset": "ISO-8859-1,utf-8;q=0.7,*;q=0.7", "Accept": "text/html,application/xhtml+xml,application/xml;q=0.9,*/*;q=0.8", "Accept-Encoding": "gzip, deflate", "Accept-Language": "en-us,en;q=0.5"}}, {"asr": null, "filesize": 2075384, "format_id": "243", "format_note": "360p", "fps": 30, "height": 360, "quality": 2, "tbr": 97.264, "url": "https://rr1---sn-0opoxu-ihvr.googlevideo.com/videoplayback?expire=1670725990&ei=Bu2UY4ulJaGGsfIP_eCiwA8&ip=189.173.225.87&id=o-AJhjlY7ieJeErMP7IEitRxUs_0Mc_KsiFca3XXNVk-7S&itag=243&aitags=133%2C134%2C135%2C160%2C242%2C243%2C244%2C278%2C394%2C395%2C396%2C397&source=youtube&requiressl=yes&mh=v5&mm=31%2C29&mn=sn-0opoxu-ihvr%2Csn-q4flrnee&ms=au%2Crdu&mv=m&mvi=1&pl=24&initcwndbps=777500&vprv=1&mime=video%2Fwebm&ns=j0qqX3Nl6gnr2IecQoL3Z4wJ&gir=yes&clen=2075384&dur=170.700&lmt=1541180021937145&mt=1670704150&fvip=5&keepalive=yes&fexp=24001373%2C24007246&c=WEB&txp=5532432&n=ICqElugTWcTVpO_2n&sparams=expire%2Cei%2Cip%2Cid%2Caitags%2Csource%2Crequiressl%2Cvprv%2Cmime%2Cns%2Cgir%2Cclen%2Cdur%2Clmt&lsparams=mh%2Cmm%2Cmn%2Cms%2Cmv%2Cmvi%2Cpl%2Cinitcwndbps&lsig=AG3C_xAwRQIhAJgd5GHc32U8Omz8fLn5Qz66dMk7SFj2nZgtCC7NihXsAiA44XQqX-3K13Vd2JdCWdkKxH4HEWGZ3PriTDmbKUKwRg%3D%3D&sig=AOq0QJ8wRQIgO06VAcxgaSE4CjYiquFzfSINsWIOSHHK1zksj8oBuCoCIQDX2X_tZiTpQgrF_rs3DRkaWQ5_YHca4J3WKp0PYI8p8w==", "width": 480, "ext": "webm", "vcodec": "vp9", "acodec": "none", "vbr": 97.264, "downloader_options": {"http_chunk_size": 10485760}, "container": "webm_dash", "format": "243 - 480x360 (360p)", "protocol": "https", "http_headers": {"User-Agent": "Mozilla/5.0 (Windows NT 10.0; Win64; x64) AppleWebKit/537.36 (KHTML, like Gecko) Chrome/73.0.3653.0 Safari/537.36", "Accept-Charset": "ISO-8859-1,utf-8;q=0.7,*;q=0.7", "Accept": "text/html,application/xhtml+xml,application/xml;q=0.9,*/*;q=0.8", "Accept-Encoding": "gzip, deflate", "Accept-Language": "en-us,en;q=0.5"}}, {"asr": null, "filesize": 2135824, "format_id": "135", "format_note": "480p", "fps": 30, "height": 480, "quality": 3, "tbr": 100.097, "url": "https://rr1---sn-0opoxu-ihvr.googlevideo.com/videoplayback?expire=1670725990&ei=Bu2UY4ulJaGGsfIP_eCiwA8&ip=189.173.225.87&id=o-AJhjlY7ieJeErMP7IEitRxUs_0Mc_KsiFca3XXNVk-7S&itag=135&aitags=133%2C134%2C135%2C160%2C242%2C243%2C244%2C278%2C394%2C395%2C396%2C397&source=youtube&requiressl=yes&mh=v5&mm=31%2C29&mn=sn-0opoxu-ihvr%2Csn-q4flrnee&ms=au%2Crdu&mv=m&mvi=1&pl=24&initcwndbps=777500&vprv=1&mime=video%2Fmp4&ns=j0qqX3Nl6gnr2IecQoL3Z4wJ&gir=yes&clen=2135824&dur=170.699&lmt=1580146880505228&mt=1670704150&fvip=5&keepalive=yes&fexp=24001373%2C24007246&c=WEB&txp=5532432&n=ICqElugTWcTVpO_2n&sparams=expire%2Cei%2Cip%2Cid%2Caitags%2Csource%2Crequiressl%2Cvprv%2Cmime%2Cns%2Cgir%2Cclen%2Cdur%2Clmt&lsparams=mh%2Cmm%2Cmn%2Cms%2Cmv%2Cmvi%2Cpl%2Cinitcwndbps&lsig=AG3C_xAwRQIhAPdm5EIXfO_aPSSfMfojM_SGzWywYoCL1vk0DuIziR-8AiBnaj21xAdApPCZ1sKu5viKnnDrfUbD1YfN99OPA-ZdEQ%3D%3D&sig=AOq0QJ8wRgIhAIlNOa4fKj8Qx4ZlF2k2Qso4wiOahxJvjYmtHkgv8jJAAiEAowWedrtX5W8Ko6BFMXBILX9i5lIepQ2UnRlBxTYNkI4=", "width": 640, "ext": "mp4", "vcodec": "avc1.4d401e", "acodec": "none", "vbr": 100.097, "downloader_options": {"http_chunk_size": 10485760}, "container": "mp4_dash", "format": "135 - 640x480 (480p)", "protocol": "https", "http_headers": {"User-Agent": "Mozilla/5.0 (Windows NT 10.0; Win64; x64) AppleWebKit/537.36 (KHTML, like Gecko) Chrome/73.0.3653.0 Safari/537.36", "Accept-Charset": "ISO-8859-1,utf-8;q=0.7,*;q=0.7", "Accept": "text/html,application/xhtml+xml,application/xml;q=0.9,*/*;q=0.8", "Accept-Encoding": "gzip, deflate", "Accept-Language": "en-us,en;q=0.5"}}, {"asr": null, "filesize": 2837285, "format_id": "397", "format_note": "480p", "fps": 30, "height": 480, "quality": 3, "tbr": 132.972, "url": "https://rr1---sn-0opoxu-ihvr.googlevideo.com/videoplayback?expire=1670725990&ei=Bu2UY4ulJaGGsfIP_eCiwA8&ip=189.173.225.87&id=o-AJhjlY7ieJeErMP7IEitRxUs_0Mc_KsiFca3XXNVk-7S&itag=397&aitags=133%2C134%2C135%2C160%2C242%2C243%2C244%2C278%2C394%2C395%2C396%2C397&source=youtube&requiressl=yes&mh=v5&mm=31%2C29&mn=sn-0opoxu-ihvr%2Csn-q4flrnee&ms=au%2Crdu&mv=m&mvi=1&pl=24&initcwndbps=777500&vprv=1&mime=video%2Fmp4&ns=j0qqX3Nl6gnr2IecQoL3Z4wJ&gir=yes&clen=2837285&dur=170.699&lmt=1633393811147835&mt=1670704150&fvip=5&keepalive=yes&fexp=24001373%2C24007246&c=WEB&txp=5532434&n=ICqElugTWcTVpO_2n&sparams=expire%2Cei%2Cip%2Cid%2Caitags%2Csource%2Crequiressl%2Cvprv%2Cmime%2Cns%2Cgir%2Cclen%2Cdur%2Clmt&lsparams=mh%2Cmm%2Cmn%2Cms%2Cmv%2Cmvi%2Cpl%2Cinitcwndbps&lsig=AG3C_xAwRQIgGUAcfwgvXYE6TIBFpqd7CRKuTGPYlphoKuAwxbfLggkCIQCB3PQMi39gzM0S_Sh2skx2dEGuHA1k3wHLQv_Tr74xDg%3D%3D&sig=AOq0QJ8wRAIgWxiNI0vly5Op3r9IN-LxRhRFL_-itehjVTzY0cPRckoCIDi1DnsJLX3ntg97EKN3T6uoM5sD8h_nn-6fzm62htkz", "width": 640, "ext": "mp4", "vcodec": "av01.0.04M.08", "acodec": "none", "vbr": 132.972, "downloader_options": {"http_chunk_size": 10485760}, "container": "mp4_dash", "format": "397 - 640x480 (480p)", "protocol": "https", "http_headers": {"User-Agent": "Mozilla/5.0 (Windows NT 10.0; Win64; x64) AppleWebKit/537.36 (KHTML, like Gecko) Chrome/73.0.3653.0 Safari/537.36", "Accept-Charset": "ISO-8859-1,utf-8;q=0.7,*;q=0.7", "Accept": "text/html,application/xhtml+xml,application/xml;q=0.9,*/*;q=0.8", "Accept-Encoding": "gzip, deflate", "Accept-Language": "en-us,en;q=0.5"}}, {"asr": null, "filesize": 3526927, "format_id": "244", "format_note": "480p", "fps": 30, "height": 480, "quality": 3, "tbr": 165.292, "url": "https://rr1---sn-0opoxu-ihvr.googlevideo.com/videoplayback?expire=1670725990&ei=Bu2UY4ulJaGGsfIP_eCiwA8&ip=189.173.225.87&id=o-AJhjlY7ieJeErMP7IEitRxUs_0Mc_KsiFca3XXNVk-7S&itag=244&aitags=133%2C134%2C135%2C160%2C242%2C243%2C244%2C278%2C394%2C395%2C396%2C397&source=youtube&requiressl=yes&mh=v5&mm=31%2C29&mn=sn-0opoxu-ihvr%2Csn-q4flrnee&ms=au%2Crdu&mv=m&mvi=1&pl=24&initcwndbps=777500&vprv=1&mime=video%2Fwebm&ns=j0qqX3Nl6gnr2IecQoL3Z4wJ&gir=yes&clen=3526927&dur=170.700&lmt=1541180021952598&mt=1670704150&fvip=5&keepalive=yes&fexp=24001373%2C24007246&c=WEB&txp=5532432&n=ICqElugTWcTVpO_2n&sparams=expire%2Cei%2Cip%2Cid%2Caitags%2Csource%2Crequiressl%2Cvprv%2Cmime%2Cns%2Cgir%2Cclen%2Cdur%2Clmt&lsparams=mh%2Cmm%2Cmn%2Cms%2Cmv%2Cmvi%2Cpl%2Cinitcwndbps&lsig=AG3C_xAwRQIgBRl2g4cBiq7W9JxH9WcKWCk2HohhLBYWTsQRhBdL89gCIQCC_PWD4Acj3weSTSDCIhJfHLrYyQXPIeQw5-7fT4sJ5Q%3D%3D&sig=AOq0QJ8wRAIgNRixZzwyOMJfnX3UDUQWuYt-D_8uGBDfHHq55c5EOUMCIBOTppsoWb2M8rxgvvIUuLTo2X_mT9T1DIaXeXOeyy_p", "width": 640, "ext": "webm", "vcodec": "vp9", "acodec": "none", "vbr": 165.292, "downloader_options": {"http_chunk_size": 10485760}, "container": "webm_dash", "format": "244 - 640x480 (480p)", "protocol": "https", "http_headers": {"User-Agent": "Mozilla/5.0 (Windows NT 10.0; Win64; x64) AppleWebKit/537.36 (KHTML, like Gecko) Chrome/73.0.3653.0 Safari/537.36", "Accept-Charset": "ISO-8859-1,utf-8;q=0.7,*;q=0.7", "Accept": "text/html,application/xhtml+xml,application/xml;q=0.9,*/*;q=0.8", "Accept-Encoding": "gzip, deflate", "Accept-Language": "en-us,en;q=0.5"}}, {"asr": 44100, "filesize": null, "format_id": "18", "format_note": "360p", "fps": 30, "height": 360, "quality": 2, "tbr": 184.435, "url": "https://rr1---sn-0opoxu-ihvr.googlevideo.com/videoplayback?expire=1670725990&ei=Bu2UY4ulJaGGsfIP_eCiwA8&ip=189.173.225.87&id=o-AJhjlY7ieJeErMP7IEitRxUs_0Mc_KsiFca3XXNVk-7S&itag=18&source=youtube&requiressl=yes&mh=v5&mm=31%2C29&mn=sn-0opoxu-ihvr%2Csn-q4flrnee&ms=au%2Crdu&mv=m&mvi=1&pl=24&initcwndbps=777500&vprv=1&mime=video%2Fmp4&ns=22jyaY6S3v50eh1q1xZHnE8J&cnr=14&ratebypass=yes&dur=170.829&lmt=1664426969203296&mt=1670704150&fvip=5&fexp=24001373%2C24007246&c=WEB&txp=5538434&n=5qh2J59t4H1JC-kAY&sparams=expire%2Cei%2Cip%2Cid%2Citag%2Csource%2Crequiressl%2Cvprv%2Cmime%2Cns%2Ccnr%2Cratebypass%2Cdur%2Clmt&lsparams=mh%2Cmm%2Cmn%2Cms%2Cmv%2Cmvi%2Cpl%2Cinitcwndbps&lsig=AG3C_xAwRQIgItbv5C2sIBpAt-9gFHhH37UVrn9mgRXtEgVeKS-DsncCIQC0AwRtzzSUguRgEPWKkILURm1ouAJlJEKVhOmplPUw0g%3D%3D&sig=AOq0QJ8wRQIhAIok-rQdkA37aBf9Wpn6uUh479h3vUHT9Zfs3wHeMt6zAiBXL4xT7mVR2dv2XLonVZ52dAGCkwR258W8lcbbrFtMsA==", "width": 480, "ext": "mp4", "vcodec": "avc1.42001E", "acodec": "mp4a.40.2", "format": "18 - 480x360 (360p)", "protocol": "https", "http_headers": {"User-Agent": "Mozilla/5.0 (Windows NT 10.0; Win64; x64) AppleWebKit/537.36 (KHTML, like Gecko) Chrome/73.0.3653.0 Safari/537.36", "Accept-Charset": "ISO-8859-1,utf-8;q=0.7,*;q=0.7", "Accept": "text/html,application/xhtml+xml,application/xml;q=0.9,*/*;q=0.8", "Accept-Encoding": "gzip, deflate", "Accept-Language": "en-us,en;q=0.5"}}], "thumbnails": [{"height": 94, "url": "https://i.ytimg.com/vi/2BYody7JX_w/hqdefault.jpg?sqp=-oaymwEbCKgBEF5IVfKriqkDDggBFQAAiEIYAXABwAEG&rs=AOn4CLAKcLZ8DpYOwPzsHYlEySdmuJFPPg", "width": 168, "resolution": "168x94", "id": "0"}, {"height": 110, "url": "https://i.ytimg.com/vi/2BYody7JX_w/hqdefault.jpg?sqp=-oaymwEbCMQBEG5IVfKriqkDDggBFQAAiEIYAXABwAEG&rs=AOn4CLCd4W9vc94dYj1geWFPNb25K9cnVQ", "width": 196, "resolution": "196x110", "id": "1"}, {"height": 138, "url": "https://i.ytimg.com/vi/2BYody7JX_w/hqdefault.jpg?sqp=-oaymwEcCPYBEIoBSFXyq4qpAw4IARUAAIhCGAFwAcABBg==&rs=AOn4CLBklgeL-OjTfokm61vb9mYXsm6zPw", "width": 246, "resolution": "246x138", "id": "2"}, {"height": 188, "url": "https://i.ytimg.com/vi/2BYody7JX_w/hqdefault.jpg?sqp=-oaymwEcCNACELwBSFXyq4qpAw4IARUAAIhCGAFwAcABBg==&rs=AOn4CLBhluvdonU0AzZ1xLr-Nim4xsjrwQ", "width": 336, "resolution": "336x188", "id": "3"}], "description": "UNO DE LOS MEJORES TRIOS QUE HA DADO LATINOAMERICA. HE OIDO QUE DOS MEXICANOS Y UN BORICUA CANTANDO EN ESTE TRIO. SUERTE Y ESPERO QUE AGRADES.", "upload_date": "20110604", "uploader": "DrJamesAQuevort", "uploader_id": "DrJamesAQuevort", "uploader_url": "http://www.youtube.com/user/DrJamesAQuevort", "channel_id": "UCq1TDMr544sVUujqXGFvLZw", "channel_url": "https://www.youtube.com/channel/UCq1TDMr544sVUujqXGFvLZw", "duration": 171, "view_count": 4803120, "average_rating": null, "age_limit": 0, "webpage_url": "https://www.youtube.com/watch?v=2BYody7JX_w", "categories": ["Music"], "tags": ["LOS", "PANCHOS"], "is_live": null, "channel": "DrJamesAQuevort", "extractor": "youtube", "webpage_url_basename": "watch", "extractor_key": "Youtube", "playlist": null, "playlist_index": null, "thumbnail": "https://i.ytimg.com/vi/2BYody7JX_w/hqdefault.jpg?sqp=-oaymwEcCNACELwBSFXyq4qpAw4IARUAAIhCGAFwAcABBg==&rs=AOn4CLBhluvdonU0AzZ1xLr-Nim4xsjrwQ", "display_id": "2BYody7JX_w", "asr": 44100, "filesize": null, "format_id": "18", "format_note": "360p", "fps": 30, "height": 360, "quality": 2, "tbr": 184.435, "url": "https://rr1---sn-0opoxu-ihvr.googlevideo.com/videoplayback?expire=1670725990&ei=Bu2UY4ulJaGGsfIP_eCiwA8&ip=189.173.225.87&id=o-AJhjlY7ieJeErMP7IEitRxUs_0Mc_KsiFca3XXNVk-7S&itag=18&source=youtube&requiressl=yes&mh=v5&mm=31%2C29&mn=sn-0opoxu-ihvr%2Csn-q4flrnee&ms=au%2Crdu&mv=m&mvi=1&pl=24&initcwndbps=777500&vprv=1&mime=video%2Fmp4&ns=22jyaY6S3v50eh1q1xZHnE8J&cnr=14&ratebypass=yes&dur=170.829&lmt=1664426969203296&mt=1670704150&fvip=5&fexp=24001373%2C24007246&c=WEB&txp=5538434&n=5qh2J59t4H1JC-kAY&sparams=expire%2Cei%2Cip%2Cid%2Citag%2Csource%2Crequiressl%2Cvprv%2Cmime%2Cns%2Ccnr%2Cratebypass%2Cdur%2Clmt&lsparams=mh%2Cmm%2Cmn%2Cms%2Cmv%2Cmvi%2Cpl%2Cinitcwndbps&lsig=AG3C_xAwRQIgItbv5C2sIBpAt-9gFHhH37UVrn9mgRXtEgVeKS-DsncCIQC0AwRtzzSUguRgEPWKkILURm1ouAJlJEKVhOmplPUw0g%3D%3D&sig=AOq0QJ8wRQIhAIok-rQdkA37aBf9Wpn6uUh479h3vUHT9Zfs3wHeMt6zAiBXL4xT7mVR2dv2XLonVZ52dAGCkwR258W8lcbbrFtMsA==", "width": 480, "ext": "mp4", "vcodec": "avc1.42001E", "acodec": "mp4a.40.2", "format": "18 - 480x360 (360p)", "protocol": "https", "http_headers": {"User-Agent": "Mozilla/5.0 (Windows NT 10.0; Win64; x64) AppleWebKit/537.36 (KHTML, like Gecko) Chrome/73.0.3653.0 Safari/537.36", "Accept-Charset": "ISO-8859-1,utf-8;q=0.7,*;q=0.7", "Accept": "text/html,application/xhtml+xml,application/xml;q=0.9,*/*;q=0.8", "Accept-Encoding": "gzip, deflate", "Accept-Language": "en-us,en;q=0.5"}, "fulltitle": "LOS PANCHOS - RAYITO DE LUNA", "_filename": "LOS PANCHOS - RAYITO DE LUNA-2BYody7JX_w.mp4"}