{"id": "r-I8B2Ria6A", "title": "Sigo siendo heterosexual", "formats": [{"asr": 48000, "filesize": 1128932, "format_id": "249", "format_note": "tiny", "fps": null, "height": null, "quality": 0, "tbr": 48.044, "url": "https://rr4---sn-0opoxu-ihv6.googlevideo.com/videoplayback?expire=1670726085&ei=ZO2UY5S7NtiSkwaw1bSACA&ip=189.173.225.87&id=o-AB4NGmQJQ6PVD6dIFK84GDF2-6IiDKCD93hdOzwTI5tq&itag=249&source=youtube&requiressl=yes&mh=_z&mm=31%2C29&mn=sn-0opoxu-ihv6%2Csn-q4fl6n6d&ms=au%2Crdu&mv=m&mvi=4&pcm2cms=yes&pl=24&gcr=mx&initcwndbps=777500&vprv=1&mime=audio%2Fwebm&ns=L8fFx7Os8GesLapy__t6bXcJ&gir=yes&clen=1128932&dur=187.981&lmt=1565928824998980&mt=1670704150&fvip=2&keepalive=yes&fexp=24001373%2C24007246&c=WEB&txp=1311222&n=z-Ow9koUrbTefu-78&sparams=expire%2Cei%2Cip%2Cid%2Citag%2Csource%2Crequiressl%2Cgcr%2Cvprv%2Cmime%2Cns%2Cgir%2Cclen%2Cdur%2Clmt&lsparams=mh%2Cmm%2Cmn%2Cms%2Cmv%2Cmvi%2Cpcm2cms%2Cpl%2Cinitcwndbps&lsig=AG3C_xAwRQIhAI4hNr4mtjUmMoHR0K8fo4N6hZ-pThvycfvWv_mnKZvnAiA1sszAjulkvFo9GXPo-jgEBgJiyRKcnxwxdrPt9hLr_w%3D%3D&sig=AOq0QJ8wRQIhANoxIzurljKmj-1CSigGAex03j4u8gXPbsGBlHZTJcRDAiA6n2iBjzgrMAaFXWe4A-rXloMEjEc1HFvSnEUgBbz6AQ==", "width": null, "ext": "webm", "vcodec": "none", "acodec": "opus", "abr": 48.044, "downloader_options": {"http_chunk_size": 10485760}, "container": "webm_dash", "format": "249 - audio only (tiny)", "protocol": "https", "http_headers": {"User-Agent": "Mozilla/5.0 (Windows NT 10.0; Win64; x64) AppleWebKit/537.36 (KHTML, like Gecko) Chrome/75.0.3745.5 Safari/537.36", "Accept-Charset": "ISO-8859-1,utf-8;q=0.7,*;q=0.7", "Accept": "text/html,application/xhtml+xml,application/xml;q=0.9,*/*;q=0.8", "Accept-Encoding": "gzip, deflate", "Accept-Language": "en-us,en;q=0.5"}}, {"asr": 48000, "filesize": 1494892, "format_id": "250", "format_note": "tiny", "fps": null, "height": null, "quality": 0, "tbr": 63.618, "url": "https://rr4---sn-0opoxu-ihv6.googlevideo.com/videoplayback?expire=1670726085&ei=ZO2UY5S7NtiSkwaw1bSACA&ip=189.173.225.87&id=o-AB4NGmQJQ6PVD6dIFK84GDF2-6IiDKCD93hdOzwTI5tq&itag=250&source=youtube&requiressl=yes&mh=_z&mm=31%2C29&mn=sn-0opoxu-ihv6%2Csn-q4fl6n6d&ms=au%2Crdu&mv=m&mvi=4&pcm2cms=yes&pl=24&gcr=mx&initcwndbps=777500&vprv=1&mime=audio%2Fwebm&ns=L8fFx7Os8GesLapy__t6bXcJ&gir=yes&clen=1494892&dur=187.981&lmt=1565928826087137&mt=1670704150&fvip=2&keepalive=yes&fexp=24001373%2C24007246&c=WEB&txp=1311222&n=z-Ow9koUrbTefu-78&sparams=expire%2Cei%2Cip%2Cid%2Citag%2Csource%2Crequiressl%2Cgcr%2Cvprv%2Cmime%2Cns%2Cgir%2Cclen%2Cdur%2Clmt&lsparams=mh%2Cmm%2Cmn%2Cms%2Cmv%2Cmvi%2Cpcm2cms%2Cpl%2Cinitcwndbps&lsig=AG3C_xAwRgIhALCJCSwMo-jZnLXPYFpI4TQ8XOp14udyvz3zHioAedw5AiEArG1zgltBgrMHCrUKCNfaFvAWb-Z1092tN2Equ0cIbLw%3D&sig=AOq0QJ8wRQIgG1qtBJZZO6XR2D-m2GoOQ2HSWwwhFNSbyMQoTGhoBd4CIQDn5pu0DpjQi8yiaj7SRy0Z7cMc0k7iZqAlB2ulVlejfQ==", "width": null, "ext": "webm", "vcodec": "none", "acodec": "opus", "abr": 63.618, "downloader_options": {"http_chunk_size": 10485760}, "container": "webm_dash", "format": "250 - audio only (tiny)", "protocol": "https", "http_headers": {"User-Agent": "Mozilla/5.0 (Windows NT 10.0; Win64; x64) AppleWebKit/537.36 (KHTML, like Gecko) Chrome/75.0.3745.5 Safari/537.36", "Accept-Charset": "ISO-8859-1,utf-8;q=0.7,*;q=0.7", "Accept": "text/html,application/xhtml+xml,application/xml;q=0.9,*/*;q=0.8", "Accept-Encoding": "gzip, deflate", "Accept-Language": "en-us,en;q=0.5"}}, {"asr": 48000, "filesize": 3005801, "format_id": "251", "format_note": "tiny", "fps": null, "height": null, "quality": 0, "tbr": 127.919, "url": "https://rr4---sn-0opoxu-ihv6.googlevideo.com/videoplayback?expire=1670726085&ei=ZO2UY5S7NtiSkwaw1bSACA&ip=189.173.225.87&id=o-AB4NGmQJQ6PVD6dIFK84GDF2-6IiDKCD93hdOzwTI5tq&itag=251&source=youtube&requiressl=yes&mh=_z&mm=31%2C29&mn=sn-0opoxu-ihv6%2Csn-q4fl6n6d&ms=au%2Crdu&mv=m&mvi=4&pcm2cms=yes&pl=24&gcr=mx&initcwndbps=777500&vprv=1&mime=audio%2Fwebm&ns=L8fFx7Os8GesLapy__t6bXcJ&gir=yes&clen=3005801&dur=187.981&lmt=1565928827767418&mt=1670704150&fvip=2&keepalive=yes&fexp=24001373%2C24007246&c=WEB&txp=1311222&n=z-Ow9koUrbTefu-78&sparams=expire%2Cei%2Cip%2Cid%2Citag%2Csource%2Crequiressl%2Cgcr%2Cvprv%2Cmime%2Cns%2Cgir%2Cclen%2Cdur%2Clmt&lsparams=mh%2Cmm%2Cmn%2Cms%2Cmv%2Cmvi%2Cpcm2cms%2Cpl%2Cinitcwndbps&lsig=AG3C_xAwRQIgEaEV4H6BA0VSFFy3h_DSYRkhcuirT6tRC6RFb0wtiA4CIQDltogTfLt-C9-SddV9spjzW8nP0zpLfAwwlO4D6gv7KQ%3D%3D&sig=AOq0QJ8wRQIgG_Y6DN7Br4A7-fX0UAruAkqXThHQimZFwXa2O8QyB64CIQCHpJqRKY402EQi9B4-p0j26lOk-UbcbOLnIET0usQNxw==", "width": null, "ext": "webm", "vcodec": "none", "acodec": "opus", "abr": 127.919, "downloader_options": {"http_chunk_size": 10485760}, "container": "webm_dash", "format": "251 - audio only (tiny)", "protocol": "https", "http_headers": {"User-Agent": "Mozilla/5.0 (Windows NT 10.0; Win64; x64) AppleWebKit/537.36 (KHTML, like Gecko) Chrome/75.0.3745.5 Safari/537.36", "Accept-Charset": "ISO-8859-1,utf-8;q=0.7,*;q=0.7", "Accept": "text/html,application/xhtml+xml,application/xml;q=0.9,*/*;q=0.8", "Accept-Encoding": "gzip, deflate", "Accept-Language": "en-us,en;q=0.5"}}, {"asr": 44100, "filesize": 3045238, "format_id": "140", "format_note": "tiny", "fps": null, "height": null, "quality": 0, "tbr": 129.612, "url": "https://rr4---sn-0opoxu-ihv6.googlevideo.com/videoplayback?expire=1670726085&ei=ZO2UY5S7NtiSkwaw1bSACA&ip=189.173.225.87&id=o-AB4NGmQJQ6PVD6dIFK84GDF2-6IiDKCD93hdOzwTI5tq&itag=140&source=youtube&requiressl=yes&mh=_z&mm=31%2C29&mn=sn-0opoxu-ihv6%2Csn-q4fl6n6d&ms=au%2Crdu&mv=m&mvi=4&pcm2cms=yes&pl=24&gcr=mx&initcwndbps=777500&vprv=1&mime=audio%2Fmp4&ns=L8fFx7Os8GesLapy__t6bXcJ&gir=yes&clen=3045238&dur=187.959&lmt=1565927848121617&mt=1670704150&fvip=2&keepalive=yes&fexp=24001373%2C24007246&c=WEB&txp=1311222&n=z-Ow9koUrbTefu-78&sparams=expire%2Cei%2Cip%2Cid%2Citag%2Csource%2Crequiressl%2Cgcr%2Cvprv%2Cmime%2Cns%2Cgir%2Cclen%2Cdur%2Clmt&lsparams=mh%2Cmm%2Cmn%2Cms%2Cmv%2Cmvi%2Cpcm2cms%2Cpl%2Cinitcwndbps&lsig=AG3C_xAwRQIhAPrAT-3ugWthTdD7oYBiGmwoHLhGKTobej5atjftSc1UAiB_UmD7JBVMzf4x35lVuBHHcUWvNmABZYGm6mLrhoID4g%3D%3D&sig=AOq0QJ8wRgIhAM7mG51VzR4-KmwP5RjG5s5igXeMOR7c6yMA1zWz8aGiAiEA1ZjyeyBnPqwMYabVlrZara3clTBfYvll72H-7FWdKOQ=", "width": null, "ext": "m4a", "vcodec": "none", "acodec": "mp4a.40.2", "abr": 129.612, "downloader_options": {"http_chunk_size": 10485760}, "container": "m4a_dash", "format": "140 - audio only (tiny)", "protocol": "https", "http_headers": {"User-Agent": "Mozilla/5.0 (Windows NT 10.0; Win64; x64) AppleWebKit/537.36 (KHTML, like Gecko) Chrome/75.0.3745.5 Safari/537.36", "Accept-Charset": "ISO-8859-1,utf-8;q=0.7,*;q=0.7", "Accept": "text/html,application/xhtml+xml,application/xml;q=0.9,*/*;q=0.8", "Accept-Encoding": "gzip, deflate", "Accept-Language": "en-us,en;q=0.5"}}, {"asr": null, "filesize": 503695, "format_id": "278", "format_note": "144p", "fps": 25, "height": 144, "quality": 0, "tbr": 21.438, "url": "https://rr4---sn-0opoxu-ihv6.googlevideo.com/videoplayback?expire=1670726085&ei=ZO2UY5S7NtiSkwaw1bSACA&ip=189.173.225.87&id=o-AB4NGmQJQ6PVD6dIFK84GDF2-6IiDKCD93hdOzwTI5tq&itag=278&aitags=133%2C134%2C135%2C136%2C160%2C242%2C243%2C244%2C247%2C278&source=youtube&requiressl=yes&mh=_z&mm=31%2C29&mn=sn-0opoxu-ihv6%2Csn-q4fl6n6d&ms=au%2Crdu&mv=m&mvi=4&pcm2cms=yes&pl=24&gcr=mx&initcwndbps=777500&vprv=1&mime=video%2Fwebm&ns=L8fFx7Os8GesLapy__t6bXcJ&gir=yes&clen=503695&dur=187.960&lmt=1565929005007265&mt=1670704150&fvip=2&keepalive=yes&fexp=24001373%2C24007246&c=WEB&txp=1311222&n=z-Ow9koUrbTefu-78&sparams=expire%2Cei%2Cip%2Cid%2Caitags%2Csource%2Crequiressl%2Cgcr%2Cvprv%2Cmime%2Cns%2Cgir%2Cclen%2Cdur%2Clmt&lsparams=mh%2Cmm%2Cmn%2Cms%2Cmv%2Cmvi%2Cpcm2cms%2Cpl%2Cinitcwndbps&lsig=AG3C_xAwRAIgVk1IxrY41Y6_P75cdgkQl2PtjopVjis7DjD1W_n9dMUCIDc1PejKDr7i8s3dyo8qJqseo5_Z-v7jofLuR9uePhhO&sig=AOq0QJ8wRgIhAMc-kEy-VFyHAseR2WBwI3sz5QeYHERD8QNHBf-qo-LhAiEA1KALsiVeN8w5k3REMjx_RAiXMdy4IkqvYS2X1XkUbz8=", "width": 144, "ext": "webm", "vcodec": "vp9", "acodec": "none", "vbr": 21.438, "downloader_options": {"http_chunk_size": 10485760}, "container": "webm_dash", "format": "278 - 144x144 (144p)", "protocol": "https", "http_headers": {"User-Agent": "Mozilla/5.0 (Windows NT 10.0; Win64; x64) AppleWebKit/537.36 (KHTML, like Gecko) Chrome/75.0.3745.5 Safari/537.36", "Accept-Charset": "ISO-8859-1,utf-8;q=0.7,*;q=0.7", "Accept": "text/html,application/xhtml+xml,application/xml;q=0.9,*/*;q=0.8", "Accept-Encoding": "gzip, deflate", "Accept-Language": "en-us,en;q=0.5"}}, {"asr": null, "filesize": 839753, "format_id": "160", "format_note": "144p", "fps": 25, "height": 144, "quality": 0, "tbr": 35.741, "url": "https://rr4---sn-0opoxu-ihv6.googlevideo.com/videoplayback?expire=1670726085&ei=ZO2UY5S7NtiSkwaw1bSACA&ip=189.173.225.87&id=o-AB4NGmQJQ6PVD6dIFK84GDF2-6IiDKCD93hdOzwTI5tq&itag=160&aitags=133%2C134%2C135%2C136%2C160%2C242%2C243%2C244%2C247%2C278&source=youtube&requiressl=yes&mh=_z&mm=31%2C29&mn=sn-0opoxu-ihv6%2Csn-q4fl6n6d&ms=au%2Crdu&mv=m&mvi=4&pcm2cms=yes&pl=24&gcr=mx&initcwndbps=777500&vprv=1&mime=video%2Fmp4&ns=L8fFx7Os8GesLapy__t6bXcJ&gir=yes&clen=839753&dur=187.960&lmt=1565927852846906&mt=1670704150&fvip=2&keepalive=yes&fexp=24001373%2C24007246&c=WEB&txp=1311222&n=z-Ow9koUrbTefu-78&sparams=expire%2Cei%2Cip%2Cid%2Caitags%2Csource%2Crequiressl%2Cgcr%2Cvprv%2Cmime%2Cns%2Cgir%2Cclen%2Cdur%2Clmt&lsparams=mh%2Cmm%2Cmn%2Cms%2Cmv%2Cmvi%2Cpcm2cms%2Cpl%2Cinitcwndbps&lsig=AG3C_xAwRgIhAKzXSTzR9f5RfDn41w_jBYs7tCoLdYlWTdqIjoWZPZRnAiEA0qMlmHBDGDMDSm93M7s1lGSJhfpmGPAZZKc8XhrgiZw%3D&sig=AOq0QJ8wRAIgTq6_-fKHtn4Nv75DurwzUKYq3FE7VluNp6o_4QYihnYCICW6c2URlSWk5oNf1JM_E4nbI6hQKP0C6beOhl3G9TPx", "width": 144, "ext": "mp4", "vcodec": "avc1.4d400b", "acodec": "none", "vbr": 35.741, "downloader_options": {"http_chunk_size": 10485760}, "container": "mp4_dash", "format": "160 - 144x144 (144p)", "protocol": "https", "http_headers": {"User-Agent": "Mozilla/5.0 (Windows NT 10.0; Win64; x64) AppleWebKit/537.36 (KHTML, like Gecko) Chrome/75.0.3745.5 Safari/537.36", "Accept-Charset": "ISO-8859-1,utf-8;q=0.7,*;q=0.7", "Accept": "text/html,application/xhtml+xml,application/xml;q=0.9,*/*;q=0.8", "Accept-Encoding": "gzip, deflate", "Accept-Language": "en-us,en;q=0.5"}}, {"asr": null, "filesize": 926907, "format_id": "242", "format_note": "240p", "fps": 25, "height": 240, "quality": 1, "tbr": 39.451, "url": "https://rr4---sn-0opoxu-ihv6.googlevideo.com/videoplayback?expire=1670726085&ei=ZO2UY5S7NtiSkwaw1bSACA&ip=189.173.225.87&id=o-AB4NGmQJQ6PVD6dIFK84GDF2-6IiDKCD93hdOzwTI5tq&itag=242&aitags=133%2C134%2C135%2C136%2C160%2C242%2C243%2C244%2C247%2C278&source=youtube&requiressl=yes&mh=_z&mm=31%2C29&mn=sn-0opoxu-ihv6%2Csn-q4fl6n6d&ms=au%2Crdu&mv=m&mvi=4&pcm2cms=yes&pl=24&gcr=mx&initcwndbps=777500&vprv=1&mime=video%2Fwebm&ns=L8fFx7Os8GesLapy__t6bXcJ&gir=yes&clen=926907&dur=187.960&lmt=1565929005015936&mt=1670704150&fvip=2&keepalive=yes&fexp=24001373%2C24007246&c=WEB&txp=1311222&n=z-Ow9koUrbTefu-78&sparams=expire%2Cei%2Cip%2Cid%2Caitags%2Csource%2Crequiressl%2Cgcr%2Cvprv%2Cmime%2Cns%2Cgir%2Cclen%2Cdur%2Clmt&lsparams=mh%2Cmm%2Cmn%2Cms%2Cmv%2Cmvi%2Cpcm2cms%2Cpl%2Cinitcwndbps&lsig=AG3C_xAwRAIgLXON4mcKri0QhMHEVCmhFoWZ7joGCZ2WrQwBtMXiwjICIF4z02cNAD0hnEXFCsoHk1wci7T1O5mIPswgk0GPAbyA&sig=AOq0QJ8wRAIgUl0weXhXHt4aOoFP-_eYnG4d7NHj0PJxHd_J3Rr-a-sCIBXnrh-P8SU9PhMj6nV9Xz6FwWrD_nmDkK_pKn5vfDPR", "width": 240, "ext": "webm", "vcodec": "vp9", "acodec": "none", "vbr": 39.451, "downloader_options": {"http_chunk_size": 10485760}, "container": "webm_dash", "format": "242 - 240x240 (240p)", "protocol": "https", "http_headers": {"User-Agent": "Mozilla/5.0 (Windows NT 10.0; Win64; x64) AppleWebKit/537.36 (KHTML, like Gecko) Chrome/75.0.3745.5 Safari/537.36", "Accept-Charset": "ISO-8859-1,utf-8;q=0.7,*;q=0.7", "Accept": "text/html,application/xhtml+xml,application/xml;q=0.9,*/*;q=0.8", "Accept-Encoding": "gzip, deflate", "Accept-Language": "en-us,en;q=0.5"}}, {"asr": null, "filesize": 1932783, "format_id": "133", "format_note": "240p", "fps": 25, "height": 240, "quality": 1, "tbr": 82.263, "url": "https://rr4---sn-0opoxu-ihv6.googlevideo.com/videoplayback?expire=1670726085&ei=ZO2UY5S7NtiSkwaw1bSACA&ip=189.173.225.87&id=o-AB4NGmQJQ6PVD6dIFK84GDF2-6IiDKCD93hdOzwTI5tq&itag=133&aitags=133%2C134%2C135%2C136%2C160%2C242%2C243%2C244%2C247%2C278&source=youtube&requiressl=yes&mh=_z&mm=31%2C29&mn=sn-0opoxu-ihv6%2Csn-q4fl6n6d&ms=au%2Crdu&mv=m&mvi=4&pcm2cms=yes&pl=24&gcr=mx&initcwndbps=777500&vprv=1&mime=video%2Fmp4&ns=L8fFx7Os8GesLapy__t6bXcJ&gir=yes&clen=1932783&dur=187.960&lmt=1565927857679471&mt=1670704150&fvip=2&keepalive=yes&fexp=24001373%2C24007246&c=WEB&txp=1311222&n=z-Ow9koUrbTefu-78&sparams=expire%2Cei%2Cip%2Cid%2Caitags%2Csource%2Crequiressl%2Cgcr%2Cvprv%2Cmime%2Cns%2Cgir%2Cclen%2Cdur%2Clmt&lsparams=mh%2Cmm%2Cmn%2Cms%2Cmv%2Cmvi%2Cpcm2cms%2Cpl%2Cinitcwndbps&lsig=AG3C_xAwRQIgVVhgcxUBA49GLmrMSu73I9gxEo8g2bF0-EAebB5SEB4CIQDsisvHgzbXC09neEVLx4E90TmWxrMhG2R2B4TyeCIwKQ%3D%3D&sig=AOq0QJ8wRQIhAN9gpxsxNh-WeUzoxYbLTUdQ0pMP3xgOPEy1suxmI81NAiBBuXhGNRKuVkDeYgetNB9p6Z4iEhA1r_1Q1jMHM1inGw==", "width": 240, "ext": "mp4", "vcodec": "avc1.4d400c", "acodec": "none", "vbr": 82.263, "downloader_options": {"http_chunk_size": 10485760}, "container": "mp4_dash", "format": "133 - 240x240 (240p)", "protocol": "https", "http_headers": {"User-Agent": "Mozilla/5.0 (Windows NT 10.0; Win64; x64) AppleWebKit/537.36 (KHTML, like Gecko) Chrome/75.0.3745.5 Safari/537.36", "Accept-Charset": "ISO-8859-1,utf-8;q=0.7,*;q=0.7", "Accept": "text/html,application/xhtml+xml,application/xml;q=0.9,*/*;q=0.8", "Accept-Encoding": "gzip, deflate", "Accept-Language": "en-us,en;q=0.5"}}, {"asr": null, "filesize": 1026697, "format_id": "134", "format_note": "360p", "fps": 25, "height": 360, "quality": 2, "tbr": 43.698, "url": "https://rr4---sn-0opoxu-ihv6.googlevideo.com/videoplayback?expire=1670726085&ei=ZO2UY5S7NtiSkwaw1bSACA&ip=189.173.225.87&id=o-AB4NGmQJQ6PVD6dIFK84GDF2-6IiDKCD93hdOzwTI5tq&itag=134&aitags=133%2C134%2C135%2C136%2C160%2C242%2C243%2C244%2C247%2C278&source=youtube&requiressl=yes&mh=_z&mm=31%2C29&mn=sn-0opoxu-ihv6%2Csn-q4fl6n6d&ms=au%2Crdu&mv=m&mvi=4&pcm2cms=yes&pl=24&gcr=mx&initcwndbps=777500&vprv=1&mime=video%2Fmp4&ns=L8fFx7Os8GesLapy__t6bXcJ&gir=yes&clen=1026697&dur=187.960&lmt=1565927870852042&mt=1670704150&fvip=2&keepalive=yes&fexp=24001373%2C24007246&c=WEB&txp=1311222&n=z-Ow9koUrbTefu-78&sparams=expire%2Cei%2Cip%2Cid%2Caitags%2Csource%2Crequiressl%2Cgcr%2Cvprv%2Cmime%2Cns%2Cgir%2Cclen%2Cdur%2Clmt&lsparams=mh%2Cmm%2Cmn%2Cms%2Cmv%2Cmvi%2Cpcm2cms%2Cpl%2Cinitcwndbps&lsig=AG3C_xAwRQIgCmOXL4SoBmpwstbPI97HKetWS5v2eXNEAzI0bAMLwqYCIQCF5n1-ELyjGIu-jXRMnGejzOre-DXvpDGdDtuSwheSiw%3D%3D&sig=AOq0QJ8wRQIgYn7u4EUakD5PGkpBbbA-XA0QkfPaWlLrxIVLX2EJOjECIQDZh1fbBHY-d_0AZgGv1dRS3RVxyYKlfa_EBXSDn549LA==", "width": 362, "ext": "mp4", "vcodec": "avc1.4d4015", "acodec": "none", "vbr": 43.698, "downloader_options": {"http_chunk_size": 10485760}, "container": "mp4_dash", "format": "134 - 362x360 (360p)", "protocol": "https", "http_headers": {"User-Agent": "Mozilla/5.0 (Windows NT 10.0; Win64; x64) AppleWebKit/537.36 (KHTML, like Gecko) Chrome/75.0.3745.5 Safari/537.36", "Accept-Charset": "ISO-8859-1,utf-8;q=0.7,*;q=0.7", "Accept": "text/html,application/xhtml+xml,application/xml;q=0.9,*/*;q=0.8", "Accept-Encoding": "gzip, deflate", "Accept-Language": "en-us,en;q=0.5"}}, {"asr": null, "filesize": 1582759, "format_id": "243", "format_note": "360p", "fps": 25, "height": 360, "quality": 2, "tbr": 67.365, "url": "https://rr4---sn-0opoxu-ihv6.googlevideo.com/videoplayback?expire=1670726085&ei=ZO2UY5S7NtiSkwaw1bSACA&ip=189.173.225.87&id=o-AB4NGmQJQ6PVD6dIFK84GDF2-6IiDKCD93hdOzwTI5tq&itag=243&aitags=133%2C134%2C135%2C136%2C160%2C242%2C243%2C244%2C247%2C278&source=youtube&requiressl=yes&mh=_z&mm=31%2C29&mn=sn-0opoxu-ihv6%2Csn-q4fl6n6d&ms=au%2Crdu&mv=m&mvi=4&pcm2cms=yes&pl=24&gcr=mx&initcwndbps=777500&vprv=1&mime=video%2Fwebm&ns=L8fFx7Os8GesLapy__t6bXcJ&gir=yes&clen=1582759&dur=187.960&lmt=1565929005034595&mt=1670704150&fvip=2&keepalive=yes&fexp=24001373%2C24007246&c=WEB&txp=1311222&n=z-Ow9koUrbTefu-78&sparams=expire%2Cei%2Cip%2Cid%2Caitags%2Csource%2Crequiressl%2Cgcr%2Cvprv%2Cmime%2Cns%2Cgir%2Cclen%2Cdur%2Clmt&lsparams=mh%2Cmm%2Cmn%2Cms%2Cmv%2Cmvi%2Cpcm2cms%2Cpl%2Cinitcwndbps&lsig=AG3C_xAwRQIgOXe28hjAS9nQVSLJdeSapvdakqkeUF5Ec4CYSVUBB0wCIQCwnreLZ8zasLCNhJMhYO-VbduHUiQCDdSbyUd7Ph_E_w%3D%3D&sig=AOq0QJ8wRAIgIiMvQCj1dcBfRXrCajyh8N1rrTmv1Abr2LL8yk-XHboCIGapWKZRBsfFTh_A6u0XQfTUjBJQlm4Dhc_yAOvLEWtB", "width": 362, "ext": "webm", "vcodec": "vp9", "acodec": "none", "vbr": 67.365, "downloader_options": {"http_chunk_size": 10485760}, "container": "webm_dash", "format": "243 - 362x360 (360p)", "protocol": "https", "http_headers": {"User-Agent": "Mozilla/5.0 (Windows NT 10.0; Win64; x64) AppleWebKit/537.36 (KHTML, like Gecko) Chrome/75.0.3745.5 Safari/537.36", "Accept-Charset": "ISO-8859-1,utf-8;q=0.7,*;q=0.7", "Accept": "text/html,application/xhtml+xml,application/xml;q=0.9,*/*;q=0.8", "Accept-Encoding": "gzip, deflate", "Accept-Language": "en-us,en;q=0.5"}}, {"asr": null, "filesize": 1705961, "format_id": "135", "format_note": "480p", "fps": 25, "height": 480, "quality": 3, "tbr": 72.609, "url": "https://rr4---sn-0opoxu-ihv6.googlevideo.com/videoplayback?expire=1670726085&ei=ZO2UY5S7NtiSkwaw1bSACA&ip=189.173.225.87&id=o-AB4NGmQJQ6PVD6dIFK84GDF2-6IiDKCD93hdOzwTI5tq&itag=135&aitags=133%2C134%2C135%2C136%2C160%2C242%2C243%2C244%2C247%2C278&source=youtube&requiressl=yes&mh=_z&mm=31%2C29&mn=sn-0opoxu-ihv6%2Csn-q4fl6n6d&ms=au%2Crdu&mv=m&mvi=4&pcm2cms=yes&pl=24&gcr=mx&initcwndbps=777500&vprv=1&mime=video%2Fmp4&ns=L8fFx7Os8GesLapy__t6bXcJ&gir=yes&clen=1705961&dur=187.960&lmt=1565927852930780&mt=1670704150&fvip=2&keepalive=yes&fexp=24001373%2C24007246&c=WEB&txp=1311222&n=z-Ow9koUrbTefu-78&sparams=expire%2Cei%2Cip%2Cid%2Caitags%2Csource%2Crequiressl%2Cgcr%2Cvprv%2Cmime%2Cns%2Cgir%2Cclen%2Cdur%2Clmt&lsparams=mh%2Cmm%2Cmn%2Cms%2Cmv%2Cmvi%2Cpcm2cms%2Cpl%2Cinitcwndbps&lsig=AG3C_xAwRgIhAPy2kSLIv9OWvhY-atmNgnIHq3eNZD4EnxapnBvJPYwyAiEA42fdtsaRUgbM7qgw6uKB4pK1dD_VY78m7BkJ_o6jI3A%3D&sig=AOq0QJ8wRgIhAKgutFjkG71FYKba0vfyQyr22pOJvsq-dpkfuBbqp3YxAiEApo6bBy_u1pTfOxeUMX72CQDJMjzkXMjPTLui9OxVCas=", "width": 482, "ext": "mp4", "vcodec": "avc1.4d401e", "acodec": "none", "vbr": 72.609, "downloader_options": {"http_chunk_size": 10485760}, "container": "mp4_dash", "format": "135 - 482x480 (480p)", "protocol": "https", "http_headers": {"User-Agent": "Mozilla/5.0 (Windows NT 10.0; Win64; x64) AppleWebKit/537.36 (KHTML, like Gecko) Chrome/75.0.3745.5 Safari/537.36", "Accept-Charset": "ISO-8859-1,utf-8;q=0.7,*;q=0.7", "Accept": "text/html,application/xhtml+xml,application/xml;q=0.9,*/*;q=0.8", "Accept-Encoding": "gzip, deflate", "Accept-Language": "en-us,en;q=0.5"}}, {"asr": null, "filesize": 3158466, "format_id": "244", "format_note": "480p", "fps": 25, "height": 480, "quality": 3, "tbr": 134.431, "url": "https://rr4---sn-0opoxu-ihv6.googlevideo.com/videoplayback?expire=1670726085&ei=ZO2UY5S7NtiSkwaw1bSACA&ip=189.173.225.87&id=o-AB4NGmQJQ6PVD6dIFK84GDF2-6IiDKCD93hdOzwTI5tq&itag=244&aitags=133%2C134%2C135%2C136%2C160%2C242%2C243%2C244%2C247%2C278&source=youtube&requiressl=yes&mh=_z&mm=31%2C29&mn=sn-0opoxu-ihv6%2Csn-q4fl6n6d&ms=au%2Crdu&mv=m&mvi=4&pcm2cms=yes&pl=24&gcr=mx&initcwndbps=777500&vprv=1&mime=video%2Fwebm&ns=L8fFx7Os8GesLapy__t6bXcJ&gir=yes&clen=3158466&dur=187.960&lmt=1565929005014294&mt=1670704150&fvip=2&keepalive=yes&fexp=24001373%2C24007246&c=WEB&txp=1311222&n=z-Ow9koUrbTefu-78&sparams=expire%2Cei%2Cip%2Cid%2Caitags%2Csource%2Crequiressl%2Cgcr%2Cvprv%2Cmime%2Cns%2Cgir%2Cclen%2Cdur%2Clmt&lsparams=mh%2Cmm%2Cmn%2Cms%2Cmv%2Cmvi%2Cpcm2cms%2Cpl%2Cinitcwndbps&lsig=AG3C_xAwRgIhANuC3rRPdRHoBdOgDLLeX2N5kVuxV9tXctIe2cMRDtiFAiEAtB7eKaUrONrlz8nXukJTkd5I4PR-yYn1uwnRMNf8xGU%3D&sig=AOq0QJ8wRAIgLHyqjS_UUJUyvSR0g2EjvHaaVdTzhcI89QZmXkl-mVQCICEnDcrK4hDUX3QucNooSOcXJks5daQXTauUW3vdDigv", "width": 482, "ext": "webm", "vcodec": "vp9", "acodec": "none", "vbr": 134.431, "downloader_options": {"http_chunk_size": 10485760}, "container": "webm_dash", "format": "244 - 482x480 (480p)", "protocol": "https", "http_headers": {"User-Agent": "Mozilla/5.0 (Windows NT 10.0; Win64; x64) AppleWebKit/537.36 (KHTML, like Gecko) Chrome/75.0.3745.5 Safari/537.36", "Accept-Charset": "ISO-8859-1,utf-8;q=0.7,*;q=0.7", "Accept": "text/html,application/xhtml+xml,application/xml;q=0.9,*/*;q=0.8", "Accept-Encoding": "gzip, deflate", "Accept-Language": "en-us,en;q=0.5"}}, {"asr": null, "filesize": 2925605, "format_id": "136", "format_note": "720p", "fps": 25, "height": 720, "quality": 4, "tbr": 124.52, "url": "https://rr4---sn-0opoxu-ihv6.googlevideo.com/videoplayback?expire=1670726085&ei=ZO2UY5S7NtiSkwaw1bSACA&ip=189.173.225.87&id=o-AB4NGmQJQ6PVD6dIFK84GDF2-6IiDKCD93hdOzwTI5tq&itag=136&aitags=133%2C134%2C135%2C136%2C160%2C242%2C243%2C244%2C247%2C278&source=youtube&requiressl=yes&mh=_z&mm=31%2C29&mn=sn-0opoxu-ihv6%2Csn-q4fl6n6d&ms=au%2Crdu&mv=m&mvi=4&pcm2cms=yes&pl=24&gcr=mx&initcwndbps=777500&vprv=1&mime=video%2Fmp4&ns=L8fFx7Os8GesLapy__t6bXcJ&gir=yes&clen=2925605&dur=187.960&lmt=1565927858876954&mt=1670704150&fvip=2&keepalive=yes&fexp=24001373%2C24007246&c=WEB&txp=1311222&n=z-Ow9koUrbTefu-78&sparams=expire%2Cei%2Cip%2Cid%2Caitags%2Csource%2Crequiressl%2Cgcr%2Cvprv%2Cmime%2Cns%2Cgir%2Cclen%2Cdur%2Clmt&lsparams=mh%2Cmm%2Cmn%2Cms%2Cmv%2Cmvi%2Cpcm2cms%2Cpl%2Cinitcwndbps&lsig=AG3C_xAwRgIhANBxe2JEaDh7A8GL9bVUd2GGe0CuUUl5uaRAPV-KwyXbAiEA0JPYPrlTaAR-Umaf_8QyTOw2IfzljB9_dGSYfGgjfy8%3D&sig=AOq0QJ8wRQIhAKT-et5QxAtSeDlKdcPG20--h7Dgp2oJ8rHRkUTe1rmWAiBXMTyObTgPcLlgv7f6SbyaYqVa5kYPlqliRPcJs-MiXg==", "width": 722, "ext": "mp4", "vcodec": "avc1.4d401f", "acodec": "none", "vbr": 124.52, "downloader_options": {"http_chunk_size": 10485760}, "container": "mp4_dash", "format": "136 - 722x720 (720p)", "protocol": "https", "http_headers": {"User-Agent": "Mozilla/5.0 (Windows NT 10.0; Win64; x64) AppleWebKit/537.36 (KHTML, like Gecko) Chrome/75.0.3745.5 Safari/537.36", "Accept-Charset": "ISO-8859-1,utf-8;q=0.7,*;q=0.7", "Accept": "text/html,application/xhtml+xml,application/xml;q=0.9,*/*;q=0.8", "Accept-Encoding": "gzip, deflate", "Accept-Language": "en-us,en;q=0.5"}}, {"asr": null, "filesize": 5581954, "format_id": "247", "format_note": "720p", "fps": 25, "height": 720, "quality": 4, "tbr": 237.58, "url": "https://rr4---sn-0opoxu-ihv6.googlevideo.com/videoplayback?expire=1670726085&ei=ZO2UY5S7NtiSkwaw1bSACA&ip=189.173.225.87&id=o-AB4NGmQJQ6PVD6dIFK84GDF2-6IiDKCD93hdOzwTI5tq&itag=247&aitags=133%2C134%2C135%2C136%2C160%2C242%2C243%2C244%2C247%2C278&source=youtube&requiressl=yes&mh=_z&mm=31%2C29&mn=sn-0opoxu-ihv6%2Csn-q4fl6n6d&ms=au%2Crdu&mv=m&mvi=4&pcm2cms=yes&pl=24&gcr=mx&initcwndbps=777500&vprv=1&mime=video%2Fwebm&ns=L8fFx7Os8GesLapy__t6bXcJ&gir=yes&clen=5581954&dur=187.960&lmt=1565929005004708&mt=1670704150&fvip=2&keepalive=yes&fexp=24001373%2C24007246&c=WEB&txp=1311222&n=z-Ow9koUrbTefu-78&sparams=expire%2Cei%2Cip%2Cid%2Caitags%2Csource%2Crequiressl%2Cgcr%2Cvprv%2Cmime%2Cns%2Cgir%2Cclen%2Cdur%2Clmt&lsparams=mh%2Cmm%2Cmn%2Cms%2Cmv%2Cmvi%2Cpcm2cms%2Cpl%2Cinitcwndbps&lsig=AG3C_xAwRQIhAM4FqbJ60OiRGCEW5YXRwyoa3vryxykhsXXcu8nTXEaZAiB4uHJvVNvzsm45LB9DyfDY5FBakAV0z_kRWpFawM9zGQ%3D%3D&sig=AOq0QJ8wRQIgBn5zbhbH1GqjcaNNVInV_JoHLmbGiR1VNj5ZY321UsECIQCrs_gDSksKC68xbBGAaune7IpKNrLauPOy5IVWqdngcg==", "width": 722, "ext": "webm", "vcodec": "vp9", "acodec": "none", "vbr": 237.58, "downloader_options": {"http_chunk_size": 10485760}, "container": "webm_dash", "format": "247 - 722x720 (720p)", "protocol": "https", "http_headers": {"User-Agent": "Mozilla/5.0 (Windows NT 10.0; Win64; x64) AppleWebKit/537.36 (KHTML, like Gecko) Chrome/75.0.3745.5 Safari/537.36", "Accept-Charset": "ISO-8859-1,utf-8;q=0.7,*;q=0.7", "Accept": "text/html,application/xhtml+xml,application/xml;q=0.9,*/*;q=0.8", "Accept-Encoding": "gzip, deflate", "Accept-Language": "en-us,en;q=0.5"}}, {"asr": 44100, "filesize": null, "format_id": "18", "format_note": "360p", "fps": 25, "height": 360, "quality": 2, "tbr": 172.627, "url": "https://rr4---sn-0opoxu-ihv6.googlevideo.com/videoplayback?expire=1670726085&ei=ZO2UY5S7NtiSkwaw1bSACA&ip=189.173.225.87&id=o-AB4NGmQJQ6PVD6dIFK84GDF2-6IiDKCD93hdOzwTI5tq&itag=18&source=youtube&requiressl=yes&mh=_z&mm=31%2C29&mn=sn-0opoxu-ihv6%2Csn-q4fl6n6d&ms=au%2Crdu&mv=m&mvi=4&pcm2cms=yes&pl=24&gcr=mx&initcwndbps=777500&vprv=1&mime=video%2Fmp4&ns=elOwAxadZ6mDBJAPNSzcgccJ&cnr=14&ratebypass=yes&dur=188.011&lmt=1661454351526969&mt=1670704150&fvip=2&fexp=24001373%2C24007246&c=WEB&txp=1318224&n=iK-c-2UverAhoeKZ1&sparams=expire%2Cei%2Cip%2Cid%2Citag%2Csource%2Crequiressl%2Cgcr%2Cvprv%2Cmime%2Cns%2Ccnr%2Cratebypass%2Cdur%2Clmt&lsparams=mh%2Cmm%2Cmn%2Cms%2Cmv%2Cmvi%2Cpcm2cms%2Cpl%2Cinitcwndbps&lsig=AG3C_xAwRAIgPSt1MRv-fI8Ls2tr4q8q1XWN0ypBkX3gpX-CUbUfTFYCIFXP4XNFwp3ldjBb_nWwCiNTOgcglDbZlE9me8pBC1cW&sig=AOq0QJ8wRQIhAPPubwwEvLbnjn9aqh-IVP7Um7z62vNTuYEwQV0d6WtWAiAf9fUKzRYALhihomLFF6LbH_-FER-sLfNNovtGRHA95g==", "width": 362, "ext": "mp4", "vcodec": "avc1.42001E", "acodec": "mp4a.40.2", "format": "18 - 362x360 (360p)", "protocol": "https", "http_headers": {"User-Agent": "Mozilla/5.0 (Windows NT 10.0; Win64; x64) AppleWebKit/537.36 (KHTML, like Gecko) Chrome/75.0.3745.5 Safari/537.36", "Accept-Charset": "ISO-8859-1,utf-8;q=0.7,*;q=0.7", "Accept": "text/html,application/xhtml+xml,application/xml;q=0.9,*/*;q=0.8", "Accept-Encoding": "gzip, deflate", "Accept-Language": "en-us,en;q=0.5"}}], "thumbnails": [{"height": 94, "url": "https://i.ytimg.com/vi/r-I8B2Ria6A/hqdefault.jpg?sqp=-oaymwEbCKgBEF5IVfKriqkDDggBFQAAiEIYAXABwAEG&rs=AOn4CLDxWbPdzMJaHNz8DmSAAA8wNeomTQ", "width": 168, "resolution": "168x94", "id": "0"}, {"height": 110, "url": "https://i.ytimg.com/vi/r-I8B2Ria6A/hqdefault.jpg?sqp=-oaymwEbCMQBEG5IVfKriqkDDggBFQAAiEIYAXABwAEG&rs=AOn4CLD4A1ziaTo55UXZPccC8QuIlipcYQ", "width": 196, "resolution": "196x110", "id": "1"}, {"height": 138, "url": "https://i.ytimg.com/vi/r-I8B2Ria6A/hqdefault.jpg?sqp=-oaymwEcCPYBEIoBSFXyq4qpAw4IARUAAIhCGAFwAcABBg==&rs=AOn4CLA-HzB964XsRcWm9M5Ik-vfKLGCCQ", "width": 246, "resolution": "246x138", "id": "2"}, {"height": 188, "url": "https://i.ytimg.com/vi/r-I8B2Ria6A/hqdefault.jpg?sqp=-oaymwEcCNACELwBSFXyq4qpAw4IARUAAIhCGAFwAcABBg==&rs=AOn4CLAfvqANkKNX8oa5cVK6LTXf-_hX7w", "width": 336, "resolution": "336x188", "id": "3"}, {"height": 1080, "url": "https://i.ytimg.com/vi_webp/r-I8B2Ria6A/maxresdefault.webp", "width": 1920, "resolution": "1920x1080", "id": "4"}], "description": "Provided to YouTube by DRO/EastWest Spain\n\nSigo siendo heterosexual \u00b7 Def Con Dos\n\nArmas Pal Pueblo\n\n\u2117 1993 dro east west\n\nComposer, Lyricist: Sloopy Seconds\n\nAuto-generated by YouTube.", "upload_date": "20170317", "uploader": "Def Con Dos - Topic", "uploader_id": "UCQwUdHKMvjFHYBiGoJMT06A", "uploader_url": "http://www.youtube.com/channel/UCQwUdHKMvjFHYBiGoJMT06A", "channel_id": "UCQwUdHKMvjFHYBiGoJMT06A", "channel_url": "https://www.youtube.com/channel/UCQwUdHKMvjFHYBiGoJMT06A", "duration": 188, "view_count": 72847, "average_rating": null, "age_limit": 0, "webpage_url": "https://www.youtube.com/watch?v=r-I8B2Ria6A", "categories": ["Music"], "tags": ["Def Con Dos", "Armas Pal Pueblo", "Sigo siendo heterosexual"], "is_live": null, "album": "Armas Pal Pueblo", "artist": "Def Con Dos", "track": "Sigo siendo heterosexual", "release_date": null, "release_year": 1993, "channel": "Def Con Dos", "creator": "Def Con Dos", "alt_title": "Sigo siendo heterosexual", "extractor": "youtube", "webpage_url_basename": "watch", "extractor_key": "Youtube", "playlist": null, "playlist_index": null, "thumbnail": "https://i.ytimg.com/vi_webp/r-I8B2Ria6A/maxresdefault.webp", "display_id": "r-I8B2Ria6A", "asr": 44100, "filesize": null, "format_id": "18", "format_note": "360p", "fps": 25, "height": 360, "quality": 2, "tbr": 172.627, "url": "https://rr4---sn-0opoxu-ihv6.googlevideo.com/videoplayback?expire=1670726085&ei=ZO2UY5S7NtiSkwaw1bSACA&ip=189.173.225.87&id=o-AB4NGmQJQ6PVD6dIFK84GDF2-6IiDKCD93hdOzwTI5tq&itag=18&source=youtube&requiressl=yes&mh=_z&mm=31%2C29&mn=sn-0opoxu-ihv6%2Csn-q4fl6n6d&ms=au%2Crdu&mv=m&mvi=4&pcm2cms=yes&pl=24&gcr=mx&initcwndbps=777500&vprv=1&mime=video%2Fmp4&ns=elOwAxadZ6mDBJAPNSzcgccJ&cnr=14&ratebypass=yes&dur=188.011&lmt=1661454351526969&mt=1670704150&fvip=2&fexp=24001373%2C24007246&c=WEB&txp=1318224&n=iK-c-2UverAhoeKZ1&sparams=expire%2Cei%2Cip%2Cid%2Citag%2Csource%2Crequiressl%2Cgcr%2Cvprv%2Cmime%2Cns%2Ccnr%2Cratebypass%2Cdur%2Clmt&lsparams=mh%2Cmm%2Cmn%2Cms%2Cmv%2Cmvi%2Cpcm2cms%2Cpl%2Cinitcwndbps&lsig=AG3C_xAwRAIgPSt1MRv-fI8Ls2tr4q8q1XWN0ypBkX3gpX-CUbUfTFYCIFXP4XNFwp3ldjBb_nWwCiNTOgcglDbZlE9me8pBC1cW&sig=AOq0QJ8wRQIhAPPubwwEvLbnjn9aqh-IVP7Um7z62vNTuYEwQV0d6WtWAiAf9fUKzRYALhihomLFF6LbH_-FER-sLfNNovtGRHA95g==", "width": 362, "ext": "mp4", "vcodec": "avc1.42001E", "acodec": "mp4a.40.2", "format": "18 - 362x360 (360p)", "protocol": "https", "http_headers": {"User-Agent": "Mozilla/5.0 (Windows NT 10.0; Win64; x64) AppleWebKit/537.36 (KHTML, like Gecko) Chrome/75.0.3745.5 Safari/537.36", "Accept-Charset": "ISO-8859-1,utf-8;q=0.7,*;q=0.7", "Accept": "text/html,application/xhtml+xml,application/xml;q=0.9,*/*;q=0.8", "Accept-Encoding": "gzip, deflate", "Accept-Language": "en-us,en;q=0.5"}, "fulltitle": "Sigo siendo heterosexual", "_filename": "Sigo siendo heterosexual-r-I8B2Ria6A.mp4"}